cpp_coveralls/__init__.py
cpp_coveralls/coverage.py
cpp_coveralls/coverage_test.py
cpp_coveralls/gitrepo.py
cpp_coveralls/gitrepo_test.py
cpp_coveralls/report.py
cpp_coveralls-0.4.2.dist-info/LICENSE
cpp_coveralls-0.4.2.dist-info/METADATA
cpp_coveralls-0.4.2.dist-info/WHEEL
cpp_coveralls-0.4.2.dist-info/entry_points.txt
cpp_coveralls-0.4.2.dist-info/top_level.txt
cpp_coveralls-0.4.2.dist-info/RECORD
